openImageDatasetSDK-1.0.4.dist-info/DESCRIPTION.rst
openImageDatasetSDK-1.0.4.dist-info/METADATA
openImageDatasetSDK-1.0.4.dist-info/RECORD
openImageDatasetSDK-1.0.4.dist-info/WHEEL
openImageDatasetSDK-1.0.4.dist-info/metadata.json
openImageDatasetSDK-1.0.4.dist-info/top_level.txt
openimagedataset/__init__.py
openimagedataset/_open_image.py
openimagedataset/environ.py
openimagedataset/_utils/__init__.py
openimagedataset/_utils/image_annotation_table_loader.py
openimagedataset/_utils/image_common_types.py
openimagedataset/_utils/image_downloader.py
openimagedataset/_utils/image_selector.py
openimagedataset/_utils/telemetry_utils.py
openimagedataset/dataaccess/__init__.py
openimagedataset/dataaccess/_open_image_blob_info.py
